cxsim/__init__.py
cxsim/actions/__init__.py
cxsim/actions/action.py
cxsim/actions/action_handler.py
cxsim/actions/action_restrictions.py
cxsim/actions/standard.py
cxsim/agents/__init__.py
cxsim/agents/agent.py
cxsim/agents/item.py
cxsim/agents/population.py
cxsim/agents/tasks.py
cxsim/agents/backends/__init__.py
cxsim/agents/backends/backend.py
cxsim/agents/backends/language_backend.py
cxsim/agents/language_model_agents/__init__.py
cxsim/agents/language_model_agents/language_model_agent.py
cxsim/agents/language_model_agents/openai_agent.py
cxsim/agents/tools/__init__.py
cxsim/agents/tools/journal.py
cxsim/agents/tools/knowledge_base.py
cxsim/agents/tools/tool.py
cxsim/agents/traits/__init__.py
cxsim/agents/traits/inventory.py
cxsim/agents/traits/memory/__init__.py
cxsim/agents/traits/memory/long_term_memory.py
cxsim/agents/traits/memory/working_memory.py
cxsim/artifacts/__init__.py
cxsim/artifacts/artifact.py
cxsim/artifacts/bank.py
cxsim/artifacts/central_bank.py
cxsim/artifacts/dialogue.py
cxsim/artifacts/firm.py
cxsim/artifacts/government.py
cxsim/artifacts/gridworld.py
cxsim/artifacts/marketplace.py
cxsim/controller/__init__.py
cxsim/controller/language_model_controller.py
cxsim/econ/__init__.py
cxsim/econ/curves.py
cxsim/econ/econ_utils.py
cxsim/econ/supply.py
cxsim/environment/__init__.py
cxsim/environment/calander.py
cxsim/environment/environment.py
cxsim/environment/event.py
cxsim/environment/utilities.py
cxsim/examples/Smith1962Environment.py
cxsim/examples/__init__.py
cxsim/gui/__init__.py
cxsim/gui/agent_overview.py
cxsim/gui/logs_popup_window.py
cxsim/gui/top_panel.py
cxsim/gui/visualizer.py
cxsim/gui/worldview.py
cxsim/gui/assets/__init__.py
cxsim/gui/assets/large_icon.ico
cxsim/gui/assets/path_definition.py
cxsim/gui/tabs/__init__.py
cxsim/gui/tabs/agents_tab.py
cxsim/gui/tabs/environment_overview.py
cxsim/gui/tabs/market_tab.py
cxsim/gui/tabs/tab.py
cxsim/prompts/__init__.py
cxsim/prompts/artifact_prompts.py
cxsim/prompts/cognitive_prompt.txt
pycxsim-0.1.5.dist-info/LICENSE
pycxsim-0.1.5.dist-info/METADATA
pycxsim-0.1.5.dist-info/WHEEL
pycxsim-0.1.5.dist-info/top_level.txt
pycxsim-0.1.5.dist-info/RECORD
