Metadata-Version: 2.1
Name: pycxsim
Version: 0.1.5
Summary: PyCxsim is a framework to simulate computational agents in a confined environment.
Home-page: https://github.com/Aatamte/PyCxsim
Author: Aaron Tamte
Author-email: aaron2804@gmail.com
License: MIT
Keywords: Artificial Intelligence,Simulation
Requires-Python: >=3.7
License-File: LICENSE
Requires-Dist: pandas >=1.5.2
Requires-Dist: numpy >=1.19.5
Requires-Dist: dearpygui >=1.9.1
Requires-Dist: names >=0.3.0
Requires-Dist: openai ~=0.27.8
Requires-Dist: pathlib ~=1.0.1
Requires-Dist: tenacity ~=8.0.1
